Metadata-Version: 1.0
Name: libclimate
Version: 0.0.0.0
Summary: libCLImate, for Python
Home-page: https://github.com/synesissoftware/libCLImate.Python
Author: Matt Wilson
Author-email: matthew@synesis.com.au
License: BSD-3-Clause
Platform: UNKNOWN
